csv_schema/__init__.py
csv_schema/_version.py
csv_schema/cli.py
csv_schema/commands/__init__.py
csv_schema/commands/generate_config/__init__.py
csv_schema/commands/generate_config/cli.py
csv_schema/commands/generate_config/generate_config.py
csv_schema/commands/validate_config/__init__.py
csv_schema/commands/validate_config/cli.py
csv_schema/commands/validate_config/validate_config.py
csv_schema/commands/validate_csv/__init__.py
csv_schema/commands/validate_csv/cli.py
csv_schema/commands/validate_csv/validate_csv.py
csv_schema/core/__init__.py
csv_schema/core/exit_codes.py
csv_schema/core/utils.py
csv_schema/core/models/__init__.py
csv_schema/core/models/base_column.py
csv_schema/core/models/base_config_object.py
csv_schema/core/models/column_types.py
csv_schema/core/models/config_property.py
csv_schema/core/models/decimal_column.py
csv_schema/core/models/enum_column.py
csv_schema/core/models/integer_column.py
csv_schema/core/models/schema_config.py
csv_schema/core/models/schema_config_filename.py
csv_schema/core/models/string_column.py
csv_schema-1.1.dist-info/METADATA
csv_schema-1.1.dist-info/WHEEL
csv_schema-1.1.dist-info/entry_points.txt
csv_schema-1.1.dist-info/top_level.txt
csv_schema-1.1.dist-info/RECORD
