Metadata-Version: 2.1
Name: csv-schema
Version: 1.1
Summary: CSV file validation.
Home-page: https://github.com/pcstout/csv-schema-py
Author: Patrick Stout
Author-email: pstout@prevagroup.com
License: Unknown
Platform: UNKNOWN
Classifier: Programming Language :: Python
Classifier: Programming Language :: Python :: 3.7
Classifier: License :: OSI Approved :: Apache Software License
Classifier: Operating System :: OS Independent
